odoo/addons/product_category_level/README.rst
odoo/addons/product_category_level/__init__.py
odoo/addons/product_category_level/__manifest__.py
odoo/addons/product_category_level/demo/product_category.xml
odoo/addons/product_category_level/i18n/fr.po
odoo/addons/product_category_level/i18n/it.po
odoo/addons/product_category_level/i18n/product_category_level.pot
odoo/addons/product_category_level/models/__init__.py
odoo/addons/product_category_level/models/product_category.py
odoo/addons/product_category_level/readme/DESCRIPTION.rst
odoo/addons/product_category_level/static/description/icon.png
odoo/addons/product_category_level/static/description/index.html
odoo/addons/product_category_level/tests/__init__.py
odoo/addons/product_category_level/tests/test_category_level.py
odoo/addons/product_category_level/views/product_category.xml
odoo_addon_product_category_level-16.0.1.0.0.4.dist-info/METADATA
odoo_addon_product_category_level-16.0.1.0.0.4.dist-info/WHEEL
odoo_addon_product_category_level-16.0.1.0.0.4.dist-info/top_level.txt
odoo_addon_product_category_level-16.0.1.0.0.4.dist-info/RECORD
